quitefastmst/__init__.py
quitefastmst/quitefastmst.cpython-39-aarch64-linux-gnu.so
quitefastmst.libs/libgomp-947d5fa1.so.1.0.0
quitefastmst-0.9.0.dist-info/METADATA
quitefastmst-0.9.0.dist-info/WHEEL
quitefastmst-0.9.0.dist-info/top_level.txt
quitefastmst-0.9.0.dist-info/RECORD
quitefastmst-0.9.0.dist-info/licenses/LICENSE
