Metadata-Version: 2.4
Name: quitefastmst
Version: 0.9.0
Summary: quitefastmst: Euclidean and Mutual Reachability Minimum Spanning Trees
Home-page: https://quitefastmst.gagolewski.com/
Download-URL: https://github.com/gagolews/quitefastmst
Author: Marek Gagolewski
Author-email: marek@gagolewski.com
Maintainer: Marek Gagolewski
License: GNU Affero General Public License v3
Project-URL: Bug Tracker, https://github.com/gagolews/quitefastmst/issues
Project-URL: Documentation, https://quitefastmst.gagolewski.com/
Project-URL: Source Code, https://github.com/gagolews/quitefastmst
Project-URL: Benchmark Datasets, https://clustering-benchmarks.gagolewski.com/
Project-URL: Author, https://www.gagolewski.com/
Classifier: Programming Language :: Python
Classifier: Programming Language :: Python :: 3
Classifier: Programming Language :: Python :: 3.9
Classifier: Programming Language :: Python :: 3.10
Classifier: Programming Language :: Python :: 3.11
Classifier: Programming Language :: Python :: 3.12
Classifier: Programming Language :: Python :: 3.13
Classifier: Programming Language :: Python :: 3 :: Only
Classifier: Operating System :: Microsoft :: Windows
Classifier: Operating System :: POSIX
Classifier: Operating System :: Unix
Classifier: Operating System :: MacOS
Classifier: Intended Audience :: Science/Research
Classifier: Intended Audience :: Developers
Classifier: Development Status :: 5 - Production/Stable
Classifier: Topic :: Scientific/Engineering
Requires-Python: >=3.9
License-File: LICENSE
Requires-Dist: numpy
Requires-Dist: Cython
Dynamic: author
Dynamic: author-email
Dynamic: classifier
Dynamic: description
Dynamic: description-content-type
Dynamic: download-url
Dynamic: home-page
Dynamic: license
Dynamic: license-file
Dynamic: maintainer
Dynamic: project-url
Dynamic: requires-dist
Dynamic: requires-python
Dynamic: summary
